sco1_misc/__init__.py
sco1_misc/csv_date_trim.py
sco1_misc/prompts.py
sco1_misc-0.1.1.dist-info/entry_points.txt
sco1_misc-0.1.1.dist-info/LICENSE
sco1_misc-0.1.1.dist-info/WHEEL
sco1_misc-0.1.1.dist-info/METADATA
sco1_misc-0.1.1.dist-info/RECORD
