Metadata-Version: 2.1
Name: sco1-misc
Version: 0.1.1
Summary: A collection of miscellaneous helpers.
Home-page: https://github.com/sco1/
Author: sco1
Author-email: sco1.git@gmail.com
Requires-Python: >=3.10,<4.0
Classifier: Development Status :: 5 - Production/Stable
Classifier: Intended Audience :: Developers
Classifier: License :: OSI Approved :: MIT License
Classifier: Operating System :: OS Independent
Classifier: Programming Language :: Python :: 3
Classifier: Programming Language :: Python :: 3 :: Only
Classifier: Programming Language :: Python :: 3.10
Classifier: Typing :: Typed
Requires-Dist: click (>=8.1,<9.0)
Project-URL: Issue Tracker, https://github.com/sco1/misc/issues
Project-URL: Repository, https://github.com/sco1/misc
